{"name":"char","imagePath":"char_tex.png","SubTexture":[{"frameY":-121,"y":91,"frameWidth":256,"frameHeight":256,"width":14,"height":31,"name":"char_arm_left","frameX":-105,"x":178},{"frameY":-77,"y":186,"frameWidth":256,"frameHeight":256,"width":146,"height":44,"name":"char_head_front","frameX":-6,"x":1},{"frameY":-78,"y":232,"frameWidth":256,"frameHeight":256,"width":146,"height":43,"name":"char_head","frameX":-6,"x":1},{"frameY":-77,"y":140,"frameWidth":256,"frameHeight":256,"width":146,"height":44,"name":"char_head_back","frameX":-6,"x":1},{"frameY":-137,"y":22,"frameWidth":256,"frameHeight":256,"width":32,"height":33,"name":"char_legs","frameX":-119,"x":178},{"frameY":-120,"y":140,"frameWidth":256,"frameHeight":256,"width":44,"height":34,"name":"char_body","frameX":-108,"x":149},{"frameY":-115,"y":129,"frameWidth":256,"frameHeight":256,"width":5,"height":3,"name":"char_mouth","frameX":-118,"x":178},{"frameY":-104,"y":124,"frameWidth":256,"frameHeight":256,"width":16,"height":3,"name":"char_pupils","frameX":-112,"x":178},{"frameY":-137,"y":1,"frameWidth":256,"frameHeight":256,"width":59,"height":19,"name":"char_sword","frameX":-89,"x":178},{"width":175,"y":1,"height":137,"name":"char_pickaxe","x":1},{"frameY":-121,"y":57,"frameWidth":256,"frameHeight":256,"width":14,"height":32,"name":"char_arm_right","frameX":-139,"x":178}]}